kule_ko/__init__.py
kule_ko-1.2.5.dist-info/LICENSE
kule_ko-1.2.5.dist-info/METADATA
kule_ko-1.2.5.dist-info/WHEEL
kule_ko-1.2.5.dist-info/RECORD
