Metadata-Version: 2.3
Name: kule-ko
Version: 1.2.5
Summary: A very, very, small package to color the terminal
License: MIT
Author: kulupu ko
Author-email: the.blob.system@gmail.com
Requires-Python: >=3.13
Classifier: License :: OSI Approved :: MIT License
Classifier: Programming Language :: Python :: 3
Classifier: Programming Language :: Python :: 3.13
Project-URL: Repository, https://github.com/kulupu-ko/kule-ko.git
